{
  "comment": "Pré-normalisation argot → coréen standard pour la traduction locale (M2M-100). Tokens entiers uniquement, cas non ambigus. Sera enrichi par le lot vérifié par agents.",
  "pairs": [
    {
      "from": "갱",
      "to": "기습 공격"
    },
    {
      "from": "갱와",
      "to": "기습하러 와"
    },
    {
      "from": "서렌",
      "to": "항복"
    },
    {
      "from": "미아",
      "to": "적이 사라졌어"
    },
    {
      "from": "한타",
      "to": "팀 전투"
    },
    {
      "from": "이니시",
      "to": "전투 시작"
    },
    {
      "from": "던지지마",
      "to": "일부러 지지 마"
    },
    {
      "from": "닷지",
      "to": "큐 취소"
    },
    {
      "from": "쿨",
      "to": "재사용 대기시간"
    },
    {
      "from": "노플",
      "to": "점멸 없음"
    },
    {
      "from": "정글차이",
      "to": "정글러 실력 차이"
    },
    {
      "from": "미드차이",
      "to": "미드 실력 차이"
    },
    {
      "from": "탑차이",
      "to": "탑 실력 차이"
    },
    {
      "from": "쌉가능",
      "to": "충분히 가능해"
    },
    {
      "from": "18",
      "to": "제기랄"
    },
    {
      "from": "시1발",
      "to": "젠장"
    },
    {
      "from": "병1신",
      "to": "멍청이"
    },
    {
      "from": "씨발",
      "to": "젠장"
    },
    {
      "from": "좆까",
      "to": "꺼져"
    },
    {
      "from": "좆밥",
      "to": "형편없는 실력자"
    },
    {
      "from": "22",
      "to": "나도 동의해"
    },
    {
      "from": "지지",
      "to": "항복하자"
    },
    {
      "from": "바텀",
      "to": "아래쪽 라인"
    },
    {
      "from": "타워",
      "to": "포탑"
    },
    {
      "from": "평타",
      "to": "기본 공격"
    },
    {
      "from": "스킬샷",
      "to": "조준해서 맞히는 기술"
    },
    {
      "from": "논타겟",
      "to": "조준이 필요한 기술"
    },
    {
      "from": "그랩",
      "to": "적을 끌어오는 기술"
    },
    {
      "from": "에어본",
      "to": "공중에 띄우는 기술"
    },
    {
      "from": "백도어",
      "to": "몰래 적 기지 건물을 공격하기"
    },
    {
      "from": "스틸",
      "to": "막타를 가로채다"
    },
    {
      "from": "몰래바론",
      "to": "몰래 바론을 사냥하기"
    },
    {
      "from": "인베",
      "to": "게임 시작 직후 적 정글에 침입하기"
    },
    {
      "from": "리쉬",
      "to": "정글러의 첫 몬스터 사냥을 도와주기"
    },
    {
      "from": "풀캠",
      "to": "정글 캠프를 전부 사냥하기"
    },
    {
      "from": "동선",
      "to": "이동 경로"
    },
    {
      "from": "정글링",
      "to": "정글 몬스터 사냥"
    },
    {
      "from": "갱킹",
      "to": "기습 공격"
    },
    {
      "from": "피딩",
      "to": "반복해서 죽어 적에게 이득을 주는 것"
    },
    {
      "from": "퍼주다",
      "to": "적에게 킬을 계속 내주다"
    },
    {
      "from": "어시",
      "to": "어시스트"
    },
    {
      "from": "셧다운",
      "to": "연속 처치를 끊어 받는 보너스 골드"
    },
    {
      "from": "현상금",
      "to": "처치하면 추가 골드를 주는 현상금"
    },
    {
      "from": "처형",
      "to": "챔피언이 아닌 것에게 죽음"
    },
    {
      "from": "주도권",
      "to": "라인 주도권"
    },
    {
      "from": "반반",
      "to": "비등비등한 상황"
    },
    {
      "from": "맞라인",
      "to": "같은 라인의 상대"
    },
    {
      "from": "상성",
      "to": "상대와의 유불리 관계"
    },
    {
      "from": "카운터",
      "to": "천적"
    },
    {
      "from": "사이드",
      "to": "옆 라인"
    },
    {
      "from": "라인스왑",
      "to": "라인 위치 교체"
    },
    {
      "from": "스왑",
      "to": "자리/챔피언 교체"
    },
    {
      "from": "프리딜",
      "to": "반격받지 않고 공격하기"
    },
    {
      "from": "킬각",
      "to": "처치할 수 있는 기회"
    },
    {
      "from": "갱각",
      "to": "기습 공격의 기회"
    },
    {
      "from": "먹자",
      "to": "잡자"
    },
    {
      "from": "오픈",
      "to": "항복하는 의미로 기지를 열어 주자"
    },
    {
      "from": "이지",
      "to": "쉬운 게임이었다"
    },
    {
      "from": "끝내자",
      "to": "게임을 끝내자"
    },
    {
      "from": "밀자",
      "to": "라인을 밀고 전진하자"
    },
    {
      "from": "철거",
      "to": "포탑 파괴"
    },
    {
      "from": "설계",
      "to": "계획적으로 함정을 준비함"
    },
    {
      "from": "맵리",
      "to": "미니맵 확인"
    },
    {
      "from": "페이스체크",
      "to": "시야 없는 수풀을 몸으로 확인하기"
    },
    {
      "from": "노궁",
      "to": "궁극기 없음"
    },
    {
      "from": "노스펠",
      "to": "소환사 주문 없음"
    },
    {
      "from": "렙차",
      "to": "레벨 차이"
    },
    {
      "from": "웨이브",
      "to": "미니언 무리"
    },
    {
      "from": "라클",
      "to": "라인 미니언 정리"
    },
    {
      "from": "용혼",
      "to": "드래곤의 영혼 버프"
    },
    {
      "from": "아타칸",
      "to": "에픽 몬스터 아타칸"
    },
    {
      "from": "리롤",
      "to": "다시 뽑기"
    },
    {
      "from": "내전",
      "to": "아는 사람들끼리 하는 사설 경기"
    },
    {
      "from": "다인큐",
      "to": "여러 명이 함께 게임을 잡는 것"
    },
    {
      "from": "뚜벅이",
      "to": "이동기가 없는 챔피언"
    },
    {
      "from": "브루저",
      "to": "전사형 챔피언"
    },
    {
      "from": "왕귀",
      "to": "후반에 매우 강해짐"
    },
    {
      "from": "유통기한",
      "to": "후반에 약해지는 챔피언"
    },
    {
      "from": "템트리",
      "to": "아이템 구매 순서"
    },
    {
      "from": "오피",
      "to": "지나치게 강함"
    },
    {
      "from": "사기챔",
      "to": "너무 강한 챔피언"
    },
    {
      "from": "꿀챔",
      "to": "쉽고 강한 챔피언"
    },
    {
      "from": "1티어",
      "to": "최상위 등급 픽"
    },
    {
      "from": "리워크",
      "to": "챔피언 전면 개편"
    },
    {
      "from": "롤드컵",
      "to": "리그 오브 레전드 세계 선수권 대회"
    },
    {
      "from": "순삭",
      "to": "순식간에 삭제되듯 죽음"
    },
    {
      "from": "원콤",
      "to": "콤보 한 번에 죽음"
    },
    {
      "from": "녹았다",
      "to": "순식간에 죽었다"
    },
    {
      "from": "짤렸다",
      "to": "혼자 다니다가 잡혔다"
    },
    {
      "from": "물렸다",
      "to": "적에게 붙잡혔다"
    },
    {
      "from": "말렸다",
      "to": "성장이 막혀 뒤처졌다"
    },
    {
      "from": "터졌다",
      "to": "완전히 무너졌다"
    },
    {
      "from": "발렸다",
      "to": "일방적으로 졌다"
    },
    {
      "from": "압살",
      "to": "압도적으로 이김"
    },
    {
      "from": "찢었다",
      "to": "엄청난 활약을 했다"
    },
    {
      "from": "하드캐리",
      "to": "혼자 팀을 승리로 이끌다"
    },
    {
      "from": "멱살캐리",
      "to": "억지로 팀을 승리시키다"
    },
    {
      "from": "1대9",
      "to": "혼자서 아홉 명을 상대하듯 캐리"
    },
    {
      "from": "4대5",
      "to": "한 명이 없는 것 같은 게임"
    },
    {
      "from": "0인분",
      "to": "아무 기여도 하지 못함"
    },
    {
      "from": "1도",
      "to": "전혀"
    },
    {
      "from": "노데스",
      "to": "한 번도 죽지 않음"
    },
    {
      "from": "딜량",
      "to": "입힌 피해량"
    },
    {
      "from": "날먹",
      "to": "노력 없이 거저 이기다"
    },
    {
      "from": "운빨",
      "to": "순전히 운"
    },
    {
      "from": "숟가락",
      "to": "남의 성과에 묻어가다"
    },
    {
      "from": "넘사벽",
      "to": "넘을 수 없는 큰 격차"
    },
    {
      "from": "비비다",
      "to": "대등하게 겨루다"
    },
    {
      "from": "피지컬",
      "to": "조작 실력"
    },
    {
      "from": "뇌지컬",
      "to": "게임 이해력과 판단력"
    },
    {
      "from": "혜지",
      "to": "실력 없이 듀오에 업혀 가는 유저"
    },
    {
      "from": "원딜자르기",
      "to": "적 원거리 딜러를 먼저 암살하기"
    },
    {
      "from": "꼬라박다",
      "to": "일부러 무모하게 돌진해서 죽다"
    },
    {
      "from": "트롤픽",
      "to": "고의로 이상한 챔피언 선택"
    },
    {
      "from": "패작",
      "to": "일부러 져서 점수를 낮추는 행위"
    },
    {
      "from": "어뷰징",
      "to": "승부 조작"
    },
    {
      "from": "헬퍼",
      "to": "불법 치트 프로그램"
    },
    {
      "from": "스크립트",
      "to": "자동 조작 치트"
    },
    {
      "from": "영정",
      "to": "영구 계정 정지"
    },
    {
      "from": "빡종",
      "to": "화가 나서 게임을 꺼 버림"
    },
    {
      "from": "강종",
      "to": "강제 종료"
    },
    {
      "from": "탈롤",
      "to": "롤을 그만두다"
    },
    {
      "from": "손절",
      "to": "미련 없이 포기하고 손을 떼다"
    },
    {
      "from": "유리멘탈",
      "to": "쉽게 무너지는 멘탈"
    },
    {
      "from": "분조장",
      "to": "분노 조절을 못 하는 사람"
    },
    {
      "from": "급발진",
      "to": "갑자기 화를 폭발시키다"
    },
    {
      "from": "혈압",
      "to": "혈압이 오를 만큼 답답하다"
    },
    {
      "from": "암걸린다",
      "to": "너무 답답하다"
    },
    {
      "from": "발암",
      "to": "매우 답답하게 만드는"
    },
    {
      "from": "고구마",
      "to": "답답한 상황"
    },
    {
      "from": "사이다",
      "to": "속이 시원한 상황"
    },
    {
      "from": "뇌절",
      "to": "도가 지나치게 반복하다"
    },
    {
      "from": "남탓",
      "to": "남에게 책임을 돌리기"
    },
    {
      "from": "정치질",
      "to": "채팅으로 편을 가르고 비난하는 행위"
    },
    {
      "from": "정병",
      "to": "정신병자"
    },
    {
      "from": "폐급",
      "to": "쓸모없는 최하급"
    },
    {
      "from": "호구",
      "to": "만만한 사람"
    },
    {
      "from": "등신",
      "to": "멍청이"
    },
    {
      "from": "자강두천",
      "to": "수준 낮은 두 사람의 맞대결"
    },
    {
      "from": "중꺾마",
      "to": "중요한 것은 꺾이지 않는 마음"
    },
    {
      "from": "빌런",
      "to": "문제를 일으키는 사람"
    },
    {
      "from": "관종",
      "to": "관심받고 싶어 하는 사람"
    },
    {
      "from": "주작",
      "to": "조작된 것"
    },
    {
      "from": "박제",
      "to": "캡처해서 기록으로 남기다"
    },
    {
      "from": "저격",
      "to": "특정인을 노리고 따라다니기"
    },
    {
      "from": "방플",
      "to": "방송을 보면서 정보를 얻는 부정행위"
    },
    {
      "from": "똥싸개",
      "to": "계속 죽어서 게임을 망치는 사람"
    },
    {
      "from": "롤린이",
      "to": "롤 초보자"
    },
    {
      "from": "개꿀",
      "to": "아주 이득"
    },
    {
      "from": "갑분싸",
      "to": "갑자기 분위기가 싸해짐"
    },
    {
      "from": "브실골",
      "to": "하위 티어"
    },
    {
      "from": "플레",
      "to": "플래티넘 티어"
    },
    {
      "from": "에메",
      "to": "에메랄드 티어"
    },
    {
      "from": "다이아",
      "to": "다이아몬드 티어"
    },
    {
      "from": "그마",
      "to": "그랜드마스터 티어"
    },
    {
      "from": "즐겜러",
      "to": "재미로 게임하는 사람"
    },
    {
      "from": "빡겜러",
      "to": "진지하게 임하는 사람"
    },
    {
      "from": "서렌각",
      "to": "항복해야 할 상황이다"
    },
    {
      "from": "노서렌",
      "to": "항복하지 말자"
    },
    {
      "from": "빠대",
      "to": "일반 게임"
    },
    {
      "from": "일겜",
      "to": "일반 게임"
    },
    {
      "from": "배치",
      "to": "배치고사"
    },
    {
      "from": "연승",
      "to": "연속 승리"
    },
    {
      "from": "연패",
      "to": "연속 패배"
    },
    {
      "from": "언랭",
      "to": "랭크 배치를 보지 않은 계정/유저"
    },
    {
      "from": "다야",
      "to": "다이아몬드 티어"
    },
    {
      "from": "오피지지",
      "to": "전적 검색 사이트 OP.GG"
    },
    {
      "from": "트수",
      "to": "인터넷 방송 시청자"
    },
    {
      "from": "치지직",
      "to": "네이버의 게임 방송 플랫폼 치지직"
    },
    {
      "from": "칼픽",
      "to": "고민 없이 즉시 챔피언을 픽하는 것"
    },
    {
      "from": "후픽",
      "to": "상대 픽을 보고 나중에 픽하는 것"
    },
    {
      "from": "탑솔",
      "to": "탑 라이너"
    },
    {
      "from": "원챔",
      "to": "한 챔피언만 주로 하는 유저"
    },
    {
      "from": "챔폭",
      "to": "다룰 수 있는 챔피언의 폭"
    },
    {
      "from": "평캔",
      "to": "기본 공격 모션 캔슬"
    },
    {
      "from": "갱좀",
      "to": "갱킹 좀 와 줘"
    },
    {
      "from": "와드좀",
      "to": "와드 좀 설치해 줘"
    },
    {
      "from": "오브",
      "to": "오브젝트"
    },
    {
      "from": "포블",
      "to": "첫 포탑 파괴 보상"
    },
    {
      "from": "플레이팅",
      "to": "포탑 방패"
    },
    {
      "from": "미아핑",
      "to": "적이 사라졌다는 핑"
    },
    {
      "from": "물음표핑",
      "to": "물음표 핑"
    },
    {
      "from": "궁없음",
      "to": "궁극기가 없음"
    },
    {
      "from": "플없음",
      "to": "점멸이 없음"
    },
    {
      "from": "맞다이",
      "to": "정면 1대1 대결"
    },
    {
      "from": "조합",
      "to": "팀의 챔피언 구성"
    },
    {
      "from": "제어와드",
      "to": "제어 와드"
    },
    {
      "from": "텔포",
      "to": "순간이동 소환사 주문"
    },
    {
      "from": "스마",
      "to": "강타"
    },
    {
      "from": "봇차이",
      "to": "봇 라인의 실력 차이"
    },
    {
      "from": "서폿차이",
      "to": "서포터의 실력 차이"
    },
    {
      "from": "긁?",
      "to": "화났어?"
    },
    {
      "from": "긁혔네",
      "to": "도발에 화가 났네"
    },
    {
      "from": "분탕",
      "to": "고의로 게임/분위기를 망치는 행위 또는 그런 사람"
    },
    {
      "from": "안물안궁",
      "to": "안 물어봤고 안 궁금하다"
    },
    {
      "from": "누칼협",
      "to": "누가 칼 들고 협박했냐"
    },
    {
      "from": "고점",
      "to": "보여줄 수 있는 최고 기량"
    },
    {
      "from": "어쩔",
      "to": "어쩌라고"
    },
    {
      "from": "정신차려",
      "to": "정신 차려라"
    },
    {
      "from": "개판",
      "to": "엉망진창인 상황"
    },
    {
      "from": "캐리좀",
      "to": "캐리 좀 해 줘"
    },
    {
      "from": "버텨",
      "to": "견뎌라"
    },
    {
      "from": "조심",
      "to": "조심해"
    },
    {
      "from": "튀어",
      "to": "도망쳐"
    },
    {
      "from": "사라짐",
      "to": "시야에서 사라졌다"
    },
    {
      "from": "안보임",
      "to": "보이지 않음"
    },
    {
      "from": "친추",
      "to": "친구 추가"
    },
    {
      "from": "구멍",
      "to": "팀에서 가장 못하는 약점인 사람"
    },
    {
      "from": "잘하시네요",
      "to": "정말 잘하시네요"
    },
    {
      "from": "개못하네",
      "to": "정말 못한다"
    },
    {
      "from": "~노",
      "to": "~냐 / ~다"
    },
    {
      "from": "~누",
      "to": "~냐 / ~네"
    },
    {
      "from": "에바",
      "to": "너무 심하다"
    },
    {
      "from": "오바",
      "to": "과장하지 마 / 너무 심하다"
    },
    {
      "from": "골때리네",
      "to": "어이없고 황당하다"
    },
    {
      "from": "웃프다",
      "to": "웃기지만 슬프다"
    },
    {
      "from": "오글거려",
      "to": "민망하고 낯간지럽다"
    },
    {
      "from": "열받네",
      "to": "화가 난다"
    },
    {
      "from": "짜증나",
      "to": "짜증이 난다"
    },
    {
      "from": "때려친다",
      "to": "그만둔다"
    },
    {
      "from": "롤접",
      "to": "롤을 그만둔다"
    },
    {
      "from": "어쩌라고",
      "to": "나보고 어떻게 하라는 거냐"
    },
    {
      "from": "꼬우면",
      "to": "불만이면 / 억울하면"
    },
    {
      "from": "엿먹어",
      "to": "골탕 먹어라"
    },
    {
      "from": "아가리",
      "to": "입 닥쳐"
    },
    {
      "from": "입털다",
      "to": "잘난 척하며 함부로 말하다"
    },
    {
      "from": "빡대가리",
      "to": "아주 멍청한 사람"
    },
    {
      "from": "찐따",
      "to": "어울리지 못하는 못난 사람"
    },
    {
      "from": "허접",
      "to": "형편없다"
    },
    {
      "from": "쫄보",
      "to": "겁쟁이"
    },
    {
      "from": "쫄지마",
      "to": "겁먹지 마"
    },
    {
      "from": "꼰대",
      "to": "잔소리하는 권위적인 사람"
    },
    {
      "from": "초딩",
      "to": "초등학생"
    },
    {
      "from": "한심하네",
      "to": "한심하다"
    },
    {
      "from": "고소",
      "to": "고소하겠다"
    },
    {
      "from": "현피",
      "to": "온라인 싸움 상대를 현실에서 만나 싸움"
    },
    {
      "from": "키배",
      "to": "키보드 배틀"
    },
    {
      "from": "고트",
      "to": "역대 최고"
    },
    {
      "from": "레전드",
      "to": "전설적이다"
    },
    {
      "from": "클라스",
      "to": "수준이 다르다"
    },
    {
      "from": "참교육",
      "to": "따끔하게 혼내 주다"
    },
    {
      "from": "국룰",
      "to": "보편적으로 통용되는 규칙"
    },
    {
      "from": "만렙",
      "to": "최고 레벨"
    },
    {
      "from": "털렸다",
      "to": "일방적으로 당했다"
    },
    {
      "from": "조졌다",
      "to": "망쳤다"
    },
    {
      "from": "통수",
      "to": "뒤통수를 치다"
    },
    {
      "from": "폭망",
      "to": "완전히 망했다"
    },
    {
      "from": "나락",
      "to": "밑바닥으로 추락함"
    },
    {
      "from": "실화냐",
      "to": "이게 실제 상황이냐"
    },
    {
      "from": "팩트",
      "to": "사실"
    },
    {
      "from": "팩폭",
      "to": "반박할 수 없는 사실로 타격을 줌"
    },
    {
      "from": "뇌피셜",
      "to": "근거 없는 개인적인 추측"
    },
    {
      "from": "정신승리",
      "to": "졌는데도 이긴 것처럼 자기 합리화함"
    },
    {
      "from": "행복회로",
      "to": "근거 없이 희망적인 상상만 함"
    },
    {
      "from": "설레발",
      "to": "성급하게 김칫국 마시며 호들갑 떨다"
    },
    {
      "from": "쉴드",
      "to": "감싸고 변호하다"
    },
    {
      "from": "솔까말",
      "to": "솔직히 까놓고 말해서"
    },
    {
      "from": "케바케",
      "to": "경우에 따라 다르다"
    },
    {
      "from": "극혐",
      "to": "극도로 혐오함"
    },
    {
      "from": "인싸",
      "to": "무리에 잘 어울리는 사람"
    },
    {
      "from": "아싸",
      "to": "무리에 못 어울리는 사람"
    },
    {
      "from": "드립",
      "to": "즉흥 농담"
    },
    {
      "from": "선넘네",
      "to": "선을 넘었다"
    },
    {
      "from": "현질",
      "to": "현금으로 게임 아이템을 사다"
    },
    {
      "from": "피방",
      "to": "PC방"
    },
    {
      "from": "디코",
      "to": "디스코드"
    },
    {
      "from": "님들",
      "to": "여러분"
    },
    {
      "from": "메타",
      "to": "현재 가장 유행하는 전략"
    },
    {
      "from": "쌉-",
      "to": "아주/완전"
    },
    {
      "from": "쌉소리",
      "to": "말도 안 되는 헛소리"
    },
    {
      "from": "개소리",
      "to": "말도 안 되는 소리"
    },
    {
      "from": "꿀빨다",
      "to": "편하게 이득을 누리다"
    },
    {
      "from": "훈수",
      "to": "옆에서 참견하며 지시함"
    },
    {
      "from": "멍때리다",
      "to": "아무 생각 없이 멍하니 있다"
    },
    {
      "from": "어케함",
      "to": "어떻게 하냐"
    },
    {
      "from": "뭐임",
      "to": "뭐야 / 뭐임?"
    },
    {
      "from": "왜저럼",
      "to": "왜 저러는 거냐"
    },
    {
      "from": "극딜",
      "to": "극한의 딜"
    },
    {
      "from": "멘붕왔다",
      "to": "멘탈이 붕괴됐다"
    },
    {
      "from": "실력차이",
      "to": "실력의 차이"
    },
    {
      "from": "빨리좀",
      "to": "빨리 좀 해라"
    },
    {
      "from": "팬이에요",
      "to": "팬입니다"
    }
  ]
}